package02yxx/__init__.py
package02yxx/main.py
package02yxx-0.1.0.dist-info/LICENSE
package02yxx-0.1.0.dist-info/METADATA
package02yxx-0.1.0.dist-info/WHEEL
package02yxx-0.1.0.dist-info/top_level.txt
package02yxx-0.1.0.dist-info/RECORD
