Metadata-Version: 2.1
Name: package02yxx
Version: 0.1.0
Summary: My awesome module
Author: Your Name
Author-email: your.email@example.com
License-File: LICENSE
Requires-Dist: bleach (==6.0.0)
Requires-Dist: certifi (==2022.12.7)
Requires-Dist: charset-normalizer (==3.1.0)
Requires-Dist: docutils (==0.19)
Requires-Dist: idna (==3.4)
Requires-Dist: importlib-metadata (==6.5.0)
Requires-Dist: jaraco.classes (==3.2.3)
Requires-Dist: keyring (==23.13.1)
Requires-Dist: markdown-it-py (==2.2.0)
Requires-Dist: mdurl (==0.1.2)
Requires-Dist: more-itertools (==9.1.0)
Requires-Dist: pkginfo (==1.9.6)
Requires-Dist: Pygments (==2.15.1)
Requires-Dist: pywin32-ctypes (==0.2.0)
Requires-Dist: readme-renderer (==37.3)
Requires-Dist: requests (==2.28.2)
Requires-Dist: requests-toolbelt (==0.10.1)
Requires-Dist: rfc3986 (==2.0.0)
Requires-Dist: rich (==13.3.4)
Requires-Dist: six (==1.16.0)
Requires-Dist: twine (==4.0.2)
Requires-Dist: urllib3 (==1.26.15)
Requires-Dist: webencodings (==0.5.1)
Requires-Dist: zipp (==3.15.0)
